junos_exporter/__init__.py
junos_exporter/__main__.py
junos_exporter/api.py
junos_exporter/config.py
junos_exporter/connector.py
junos_exporter/exporter.py
junos_exporter-0.0.10.dist-info/METADATA
junos_exporter-0.0.10.dist-info/WHEEL
junos_exporter-0.0.10.dist-info/entry_points.txt
junos_exporter-0.0.10.dist-info/licenses/LICENSE
junos_exporter-0.0.10.dist-info/RECORD
