Metadata-Version: 2.4
Name: junos-exporter
Version: 0.0.10
Summary: Prometheus Exporter for Junos using PyEZ Tables and Views
Project-URL: Repository, https://github.com/minefuto/junos-exporter.git
Author-email: minefuto <minefuto@gmail.com>
License: MIT License
License-File: LICENSE
Classifier: Programming Language :: Python :: 3
Classifier: Programming Language :: Python :: 3.10
Classifier: Programming Language :: Python :: 3.11
Classifier: Programming Language :: Python :: 3.12
Classifier: Programming Language :: Python :: 3.13
Requires-Python: >=3.10
Requires-Dist: asyncssh>=2.20.0
Requires-Dist: fastapi>=0.115.8
Requires-Dist: junos-eznc>=2.7.4
Requires-Dist: ntc-templates>=7.7.0
Requires-Dist: pyyaml>=6.0.2
Requires-Dist: scrapli-netconf>=2025.1.30
Requires-Dist: uvicorn>=0.34.0
